pypi_Deploy_Demo/__init__.py
pypi_Deploy_Demo/component.py
pypi_Deploy_Demo/main.py
pypi_Deploy_Demo-0.0.4.dist-info/LICENSE
pypi_Deploy_Demo-0.0.4.dist-info/METADATA
pypi_Deploy_Demo-0.0.4.dist-info/WHEEL
pypi_Deploy_Demo-0.0.4.dist-info/entry_points.txt
pypi_Deploy_Demo-0.0.4.dist-info/top_level.txt
pypi_Deploy_Demo-0.0.4.dist-info/RECORD
