Metadata-Version: 2.1
Name: pypi-Deploy-Demo
Version: 0.0.4
Summary: pypi-Deploy-Demo
Home-page: https://github.com/Kushagrabainsla/build-flask-app
Author: Kushagra Bainsla
Author-email: kushagrabainsla@gmail.com
License: MIT
Platform: UNKNOWN
Requires-Dist: PyInquirer
